deep_dimensions/__init__.py
deep_dimensions/config/__init__.py
deep_dimensions/config/settings.py
deep_dimensions/core/__init__.py
deep_dimensions/core/autoscaler.py
deep_dimensions/core/autotuner.py
deep_dimensions/core/exceptions.py
deep_dimensions/frameworks/__init__.py
deep_dimensions/frameworks/pytorch_adapter.py
deep_dimensions/frameworks/registry.py
deep_dimensions/frameworks/tensorflow_adapter.py
deep_dimensions/interfaces/__init__.py
deep_dimensions/interfaces/framework_adapter.py
deep_dimensions/interfaces/memory_provider.py
deep_dimensions/interfaces/scaling_strategy.py
deep_dimensions/memory/__init__.py
deep_dimensions/memory/cuda.py
deep_dimensions/memory/monitor.py
deep_dimensions/memory/system.py
deep_dimensions/scaling/__init__.py
deep_dimensions/scaling/calculator.py
deep_dimensions/scaling/exponential.py
deep_dimensions/scaling/linear.py
deep_dimensions/utils/__init__.py
deep_dimensions/utils/logging.py
deep_dimensions/utils/oom.py
deep_dimensions/utils/validation.py
deep_dimensions-0.2.5.dist-info/licenses/LICENSE
deep_dimensions-0.2.5.dist-info/METADATA
deep_dimensions-0.2.5.dist-info/WHEEL
deep_dimensions-0.2.5.dist-info/top_level.txt
deep_dimensions-0.2.5.dist-info/RECORD
