Metadata-Version: 2.4
Name: deep-dimensions
Version: 0.2.5
Summary: Auto-scaling tensor dimensions for PyTorch and TensorFlow based on available RAM
Author-email: Vihaan <vihaan@example.com>
License: GPLv3
Project-URL: Homepage, https://github.com/vihaan/deep-dimensions
Project-URL: Bug Tracker, https://github.com/vihaan/deep-dimensions/issues
Keywords: pytorch,tensorflow,memory,autoscale,tensor,deep-learning
Classifier: Development Status :: 4 - Beta
Classifier: Intended Audience :: Developers
Classifier: Intended Audience :: Science/Research
Classifier: License :: OSI Approved :: GNU General Public License v3 (GPLv3)
Classifier: Programming Language :: Python :: 3
Classifier: Programming Language :: Python :: 3.8
Classifier: Programming Language :: Python :: 3.9
Classifier: Programming Language :: Python :: 3.10
Classifier: Programming Language :: Python :: 3.11
Classifier: Programming Language :: Python :: 3.12
Classifier: Topic :: Scientific/Engineering :: Artificial Intelligence
Requires-Python: >=3.8
License-File: LICENSE
Requires-Dist: psutil>=5.8.0
Provides-Extra: pytorch
Requires-Dist: torch>=1.9.0; extra == "pytorch"
Provides-Extra: tensorflow
Requires-Dist: tensorflow>=2.8.0; extra == "tensorflow"
Provides-Extra: all
Requires-Dist: torch>=1.9.0; extra == "all"
Requires-Dist: tensorflow>=2.8.0; extra == "all"
Provides-Extra: dev
Requires-Dist: pytest>=7.0.0; extra == "dev"
Requires-Dist: pytest-cov>=4.0.0; extra == "dev"
Requires-Dist: pytest-mock>=3.10.0; extra == "dev"
Requires-Dist: mypy>=1.0.0; extra == "dev"
Requires-Dist: ruff>=0.1.0; extra == "dev"
Requires-Dist: torch>=1.9.0; extra == "dev"
Requires-Dist: tensorflow>=2.8.0; extra == "dev"
Dynamic: license-file
